datatracer/__init__.py
datatracer/__main__.py
datatracer/api.py
datatracer/core.py
datatracer/data.py
datatracer/metadata.py
datatracer/column_map/__init__.py
datatracer/column_map/base.py
datatracer/column_map/basic.py
datatracer/column_map/transformer.py
datatracer/datasets/Bupa/alkphos.csv
datatracer/datasets/Bupa/bupa.csv
datatracer/datasets/Bupa/bupa_name.csv
datatracer/datasets/Bupa/bupa_type.csv
datatracer/datasets/Bupa/drinks.csv
datatracer/datasets/Bupa/gammagt.csv
datatracer/datasets/Bupa/mcv.csv
datatracer/datasets/Bupa/metadata.json
datatracer/datasets/Bupa/sgot.csv
datatracer/datasets/Bupa/sgpt.csv
datatracer/datasets/Chess/game.csv
datatracer/datasets/Chess/metadata.json
datatracer/datasets/Chess/opening.csv
datatracer/datasets/NBA/Actions.csv
datatracer/datasets/NBA/Game.csv
datatracer/datasets/NBA/Player.csv
datatracer/datasets/NBA/Team.csv
datatracer/datasets/NBA/joined_drafted_all_players_original.csv
datatracer/datasets/NBA/metadata.json
datatracer/datasets/SameGen/metadata.json
datatracer/datasets/SameGen/parent.csv
datatracer/datasets/SameGen/person.csv
datatracer/datasets/SameGen/same_gen.csv
datatracer/datasets/SameGen/target.csv
datatracer/datasets/classicmodels/customers.csv
datatracer/datasets/classicmodels/employees.csv
datatracer/datasets/classicmodels/metadata.json
datatracer/datasets/classicmodels/offices.csv
datatracer/datasets/classicmodels/orderdetails.csv
datatracer/datasets/classicmodels/orders.csv
datatracer/datasets/classicmodels/payments.csv
datatracer/datasets/classicmodels/productlines.csv
datatracer/datasets/classicmodels/products.csv
datatracer/datasets/mutagenesis/atom.csv
datatracer/datasets/mutagenesis/bond.csv
datatracer/datasets/mutagenesis/metadata.json
datatracer/datasets/mutagenesis/molecule.csv
datatracer/datasets/posts/make.py
datatracer/datasets/posts/metadata.json
datatracer/datasets/posts/posts.csv
datatracer/datasets/posts/users.csv
datatracer/datasets/pubs/authors.csv
datatracer/datasets/pubs/discounts.csv
datatracer-0.0.6.dist-info/AUTHORS.rst
datatracer-0.0.6.dist-info/LICENSE
datatracer-0.0.6.dist-info/METADATA
datatracer-0.0.6.dist-info/WHEEL
datatracer-0.0.6.dist-info/entry_points.txt
datatracer-0.0.6.dist-info/top_level.txt
datatracer-0.0.6.dist-info/RECORD
